LICENSE
MANIFEST.in
README.rst
requirements.txt
setup.py
trequests/__init__.py
trequests/trequests_version.txt
zymbit_trequests.egg-info/PKG-INFO
zymbit_trequests.egg-info/SOURCES.txt
zymbit_trequests.egg-info/dependency_links.txt
zymbit_trequests.egg-info/requires.txt
zymbit_trequests.egg-info/top_level.txt